sphinxcontrib_googleanalytics-0.4-nspkg.pth
sphinxcontrib/googleanalytics.py
sphinxcontrib_googleanalytics-0.4.dist-info/METADATA
sphinxcontrib_googleanalytics-0.4.dist-info/WHEEL
sphinxcontrib_googleanalytics-0.4.dist-info/namespace_packages.txt
sphinxcontrib_googleanalytics-0.4.dist-info/top_level.txt
sphinxcontrib_googleanalytics-0.4.dist-info/RECORD
